{
  "sections": {
    "main": {
      "type": "main-product",
      "settings": {
      }
    },
    "16426285735ee00f29": {
      "type": "product-bar",
      "settings": {
        "title": ""
      }
    },
    "164253095353d35284": {
      "type": "in-real-life",
      "disabled": true,
      "settings": {
        "title": "In Real Life"
      }
    },
    "1642702250db612244": {
      "type": "fit-guide",
      "disabled": true,
      "settings": {
        "offset_text": true,
        "use_page_width": true
      }
    }
  },
  "order": [
    "main",
    "16426285735ee00f29",
    "164253095353d35284",
    "1642702250db612244"
  ]
}
